{
	"name": "Lesson 7",
	"hint": "Teleports can be directional. The thief takes your tools. New walls can appear under you.",
	"password": "FXQO",
	"time": 150,
	"chips": 3,
	"map": {
		"width": 19,
		"height": 17,
		"strings": [
			"   ................",
			"   .##############.",
			"....#v<<<<<<<<<<<#.",
			".####v##########^#.",
			".#>@>v<@<<<<<<<#^#.",
			".#^##.########^#^#.",
			".#^#....#....*^#^#.",
			".#^#..i.#..#.*^#^#.",
			".#^#....#..#.*^#^#.",
			".#^#....#..#.*^#^#.",
			".#^####...######^#.",
			".#^~.#..#..__#>>^#.",
			".#^~.#..#..=X#^###.",
			".#^~.#..#.####^#...",
			".#^~....#...@.^#.  ",
			".###############.  ",
			".................  "
		],
		"data": [],
		"legend": []
	},
	"entities": [
		{
			"kind": "Player",
			"pos": [5, 7]
		},
		{
			"kind": "Thief",
			"pos": [5, 5]
		},
		{
			"kind": "Thief",
			"pos": [9, 13]
		},
		{
			"kind": "Flippers",
			"pos": [9, 7]
		},
		{
			"kind": "FireBoots",
			"pos": [7, 13]
		}
	]
}
